jade/__init__.py
jade/common.py
jade/enums.py
jade/events.py
jade/exceptions.py
jade/loggers.py
jade/resource_monitor.py
jade/result.py
jade/test_common.py
jade/cli/__init__.py
jade/cli/auto_config.py
jade/cli/cancel_jobs.py
jade/cli/cluster.py
jade/cli/collect_stats.py
jade/cli/common.py
jade/cli/config.py
jade/cli/db.py
jade/cli/extensions.py
jade/cli/hpc_jobs.py
jade/cli/jade.py
jade/cli/jade_internal.py
jade/cli/pipeline.py
jade/cli/prune_files.py
jade/cli/resubmit_jobs.py
jade/cli/run.py
jade/cli/run_jobs.py
jade/cli/run_multi_node_job.py
jade/cli/run_spark_cluster.py
jade/cli/show_events.py
jade/cli/show_results.py
jade/cli/show_status.py
jade/cli/spark.py
jade/cli/stats.py
jade/cli/submit_jobs.py
jade/cli/try_submit_jobs.py
jade/cli/wait.py
jade/extensions/__init__.py
jade/extensions/registry.py
jade/extensions/demo/.gitignore
jade/extensions/demo/__init__.py
jade/extensions/demo/autoregression_configuration.py
jade/extensions/demo/autoregression_execution.py
jade/extensions/demo/autoregression_inputs.py
jade/extensions/demo/autoregression_parameters.py
jade/extensions/demo/cli.py
jade/extensions/demo/create_demo_config.sh
jade/extensions/demo/create_merge_pred_gdp.py
jade/extensions/demo/merge_pred_gdp.py
jade/extensions/demo/data/inputs.json
jade/extensions/demo/data/inputs.py
jade/extensions/demo/data/gdp/license.txt
jade/extensions/demo/data/gdp/readme.txt
jade/extensions/demo/data/gdp/countries/australia.csv
jade/extensions/demo/data/gdp/countries/brazil.csv
jade/extensions/demo/data/gdp/countries/canada.csv
jade/extensions/demo/data/gdp/countries/china.csv
jade/extensions/demo/data/gdp/countries/france.csv
jade/extensions/demo/data/gdp/countries/germany.csv
jade/extensions/demo/data/gdp/countries/india.csv
jade/extensions/demo/data/gdp/countries/italy.csv
jade/extensions/demo/data/gdp/countries/japan.csv
jade/extensions/demo/data/gdp/countries/russia.csv
jade/extensions/demo/data/gdp/countries/united_kingdom.csv
nrel_jade-0.10.2.dist-info/METADATA
nrel_jade-0.10.2.dist-info/WHEEL
nrel_jade-0.10.2.dist-info/entry_points.txt
nrel_jade-0.10.2.dist-info/licenses/LICENSE
nrel_jade-0.10.2.dist-info/RECORD
