Metadata-Version: 2.3
Name: NREL-jade
Version: 0.10.2
Summary: Provides HPC workflow automation services
Project-URL: Homepage, https://github.com./NREL/jade
Maintainer-email: Daniel Thom <daniel.thom@nrel.gov>
License-File: LICENSE
Keywords: hpc,jade,workflow
Classifier: Development Status :: 4 - Beta
Classifier: License :: OSI Approved :: BSD License
Classifier: Natural Language :: English
Classifier: Programming Language :: Python :: 3.7
Requires-Python: >=3.7
Requires-Dist: click
Requires-Dist: filelock
Requires-Dist: numpy
Requires-Dist: pandas
Requires-Dist: plotly
Requires-Dist: prettytable
Requires-Dist: psutil
Requires-Dist: pyarrow
Requires-Dist: pydantic~=2.5.2
Requires-Dist: requests
Requires-Dist: tabulate
Requires-Dist: toml>=0.10.0
Provides-Extra: dataframe-utils
Requires-Dist: tables; extra == 'dataframe-utils'
Provides-Extra: demo
Requires-Dist: matplotlib; extra == 'demo'
Requires-Dist: statsmodels; extra == 'demo'
Provides-Extra: dev
Requires-Dist: black; extra == 'dev'
Requires-Dist: flake8; extra == 'dev'
Requires-Dist: ghp-import; extra == 'dev'
Requires-Dist: matplotlib; extra == 'dev'
Requires-Dist: mock>=3.0.0; extra == 'dev'
Requires-Dist: pre-commit; extra == 'dev'
Requires-Dist: pycodestyle; extra == 'dev'
Requires-Dist: pylint; extra == 'dev'
Requires-Dist: pypandoc; extra == 'dev'
Requires-Dist: pytest; extra == 'dev'
Requires-Dist: pytest-cov; extra == 'dev'
Requires-Dist: sphinx-rtd-theme>=0.4.3; extra == 'dev'
Requires-Dist: sphinx>=2.0; extra == 'dev'
Requires-Dist: sphinxcontrib-plantuml; extra == 'dev'
Requires-Dist: statsmodels; extra == 'dev'
Requires-Dist: tox; extra == 'dev'
